sqlalchemy_zipkin.py
SQLAlchemy_Zipkin-0.2.0.dist-info/LICENSE.txt
SQLAlchemy_Zipkin-0.2.0.dist-info/METADATA
SQLAlchemy_Zipkin-0.2.0.dist-info/WHEEL
SQLAlchemy_Zipkin-0.2.0.dist-info/top_level.txt
SQLAlchemy_Zipkin-0.2.0.dist-info/RECORD
