Metadata-Version: 2.1
Name: SQLAlchemy-Zipkin
Version: 0.2.0
Summary: An zipkin extension for sqlalchemy library based on py_zipkin.
Home-page: https://github.com/mklein0/sqlalchemy-zipkin
Author: Marcos Klein
Author-email: mklein0@gmail.com
License: MIT
Platform: any
Classifier: Development Status :: 3 - Alpha
Classifier: Intended Audience :: Developers
Classifier: License :: OSI Approved :: MIT License
Classifier: Programming Language :: Python
Classifier: Topic :: Software Development :: Libraries :: Python Modules
Classifier: Topic :: System :: Monitoring
Requires-Dist: py-zipkin (>=0.7.0)
Requires-Dist: SQLAlchemy (>=0.9.8)
